video_funnel/__init__.py
video_funnel/__main__.py
video_funnel/funnel.py
video_funnel/index.html
video_funnel/server.py
video_funnel/utils.py
video_funnel-0.3.1.dist-info/LICENSE
video_funnel-0.3.1.dist-info/METADATA
video_funnel-0.3.1.dist-info/WHEEL
video_funnel-0.3.1.dist-info/entry_points.txt
video_funnel-0.3.1.dist-info/top_level.txt
video_funnel-0.3.1.dist-info/RECORD
